spatial_image/__init__.py
spatial_image-1.2.2.dist-info/METADATA
spatial_image-1.2.2.dist-info/WHEEL
spatial_image-1.2.2.dist-info/licenses/LICENSE.txt
spatial_image-1.2.2.dist-info/RECORD
