Metadata-Version: 2.4
Name: spatial_image
Version: 1.2.2
Summary: A multi-dimensional spatial image data structure for scientific Python.
Author-email: Matt McCormick <matt@mmmccormick.com>
License: The MIT License (MIT)
License-File: LICENSE.txt
Classifier: Intended Audience :: Developers
Classifier: Intended Audience :: Science/Research
Classifier: License :: OSI Approved :: MIT License
Classifier: Programming Language :: Python
Classifier: Programming Language :: Python :: 3.10
Classifier: Programming Language :: Python :: 3.11
Classifier: Programming Language :: Python :: 3.12
Classifier: Programming Language :: Python :: 3.13
Requires-Python: >=3.10
Requires-Dist: numpy
Requires-Dist: xarray-dataclass>=3.0.0
Requires-Dist: xarray>=2024.10.0
